README.rst
ips.py
setup.py
python_ips.egg-info/PKG-INFO
python_ips.egg-info/SOURCES.txt
python_ips.egg-info/dependency_links.txt
python_ips.egg-info/entry_points.txt
python_ips.egg-info/requires.txt
python_ips.egg-info/top_level.txt