Metadata-Version: 1.0
Name: python-ips
Version: 2.0
Summary: Python IPS patcher.
Home-page: UNKNOWN
Author: Devon Meunier
Author-email: devon@ajah.ca
License: MIT License
Platform: UNKNOWN
